librelane/__init__.py
librelane/__main__.py
librelane/__version__.py
librelane/common/__init__.py
librelane/common/cli.py
librelane/common/drc.py
librelane/common/generic_dict.py
librelane/common/metrics/__init__.py
librelane/common/metrics/__main__.py
librelane/common/metrics/library.py
librelane/common/metrics/metric.py
librelane/common/metrics/util.py
librelane/common/misc.py
librelane/common/ring_buffer.py
librelane/common/tcl.py
librelane/common/toolbox.py
librelane/common/tpe.py
librelane/common/types.py
librelane/config/__init__.py
librelane/config/__main__.py
librelane/config/config.py
librelane/config/flow.py
librelane/config/pdk_compat.py
librelane/config/preprocessor.py
librelane/config/removals.py
librelane/config/variable.py
librelane/container.py
librelane/env_info.py
librelane/examples/hold_eco_demo/config.yaml
librelane/examples/hold_eco_demo/demo.v
librelane/examples/spm/config.yaml
librelane/examples/spm/pin_order.cfg
librelane/examples/spm/src/impl.sdc
librelane/examples/spm/src/signoff.sdc
librelane/examples/spm/src/spm.v
librelane/examples/spm/verify/spm_tb.v
librelane/examples/spm-user_project_wrapper/SPM_example.v
librelane/examples/spm-user_project_wrapper/base_sdc_file.sdc
librelane/examples/spm-user_project_wrapper/config-tut.json
librelane/examples/spm-user_project_wrapper/config.json
librelane/examples/spm-user_project_wrapper/defines.v
librelane/examples/spm-user_project_wrapper/template.def
librelane/examples/spm-user_project_wrapper/user_project_wrapper.v
librelane/flows/__init__.py
librelane/flows/builtins.py
librelane/flows/classic.py
librelane/flows/cli.py
librelane/flows/flow.py
librelane/flows/misc.py
librelane/flows/optimizing.py
librelane/flows/sequential.py
librelane/flows/synth_explore.py
librelane/help/__main__.py
librelane/logging/__init__.py
librelane/logging/logger.py
librelane/open_pdks_rev
librelane/plugins.py
librelane/py.typed
librelane/scripts/base.sdc
librelane/scripts/klayout/Readme.md
librelane-2.4.11.dist-info/METADATA
librelane-2.4.11.dist-info/WHEEL
librelane-2.4.11.dist-info/entry_points.txt
librelane-2.4.11.dist-info/RECORD
